pytest_litf.py
pytest_litf-0.1.6.data/scripts/pytest-litf
pytest_litf-0.1.6.dist-info/LICENSE
pytest_litf-0.1.6.dist-info/METADATA
pytest_litf-0.1.6.dist-info/WHEEL
pytest_litf-0.1.6.dist-info/entry_points.txt
pytest_litf-0.1.6.dist-info/top_level.txt
pytest_litf-0.1.6.dist-info/RECORD
